soraha_utils/__init__.py
soraha_utils/__init__.sync-conflict-20220211-114757-E7ASFP2.py
soraha_utils/hook.py
soraha_utils/uiclient.py
soraha_utils/uiexcep.py
soraha_utils/uihook.py
soraha_utils/uilog.py
soraha_utils/uio.py
soraha_utils/uitry.py
soraha_utils/uiutils.py
soraha_utils-0.0.17.dist-info/LICENSE
soraha_utils-0.0.17.dist-info/METADATA
soraha_utils-0.0.17.dist-info/PKG-INFO.sync-conflict-20220211-114757-E7ASFP2
soraha_utils-0.0.17.dist-info/SOURCES.sync-conflict-20220211-114757-E7ASFP2.txt
soraha_utils-0.0.17.dist-info/WHEEL
soraha_utils-0.0.17.dist-info/top_level.txt
soraha_utils-0.0.17.dist-info/RECORD
