Metadata-Version: 2.1
Name: soraha-utils
Version: 0.0.17
Summary: soraha_utils
Home-page: https://www.github.com/LYshiying/soraha_utils
Author: shiying
Author-email: 839778960@qq.com
License: UNKNOWN
Platform: UNKNOWN
Classifier: Programming Language :: Python :: 3
Classifier: Operating System :: OS Independent
Requires-Python: >=3.8
License-File: LICENSE
Requires-Dist: httpx (>=0.19.0)
Requires-Dist: ujson (>=4.1.0)
Requires-Dist: loguru (>=0.5.3)
Requires-Dist: requests (>=2.26.0)
Requires-Dist: aiofiles (>=0.7.0)
